max_number/__init__.py
max_number/__main__.py
max_number/core.py
maxnumberlib-0.1.0.dist-info/licenses/LICENSE
maxnumberlib-0.1.0.dist-info/METADATA
maxnumberlib-0.1.0.dist-info/WHEEL
maxnumberlib-0.1.0.dist-info/entry_points.txt
maxnumberlib-0.1.0.dist-info/top_level.txt
maxnumberlib-0.1.0.dist-info/RECORD
