Metadata-Version: 2.4
Name: MaxNumberLib
Version: 0.1.0
Summary: Find the maximum number from a list
Author: Mahmmed Albadwy
Author-email: Mahmmed Albadwy <mamalbadwy23@gmail.com>
License: 
Requires-Python: >=3.13
License-File: LICENSE
Dynamic: author
Dynamic: license-file
Dynamic: requires-python
